image_preprocessing/__init__.py
image_preprocessing/preprocessing/__init__.py
image_preprocessing/preprocessing/pipeline.py
image_preprocessing/preprocessing/tools.py
image_preprocessing/utils/__init__.py
image_preprocessing/utils/display_images.py
image_preprocessing/utils/io.py
img_preprocess_pipeline-0.0.2.dist-info/LICENSE
img_preprocess_pipeline-0.0.2.dist-info/METADATA
img_preprocess_pipeline-0.0.2.dist-info/WHEEL
img_preprocess_pipeline-0.0.2.dist-info/top_level.txt
img_preprocess_pipeline-0.0.2.dist-info/RECORD
