Metadata-Version: 2.1
Name: img-preprocess-pipeline
Version: 0.0.2
Summary: Customized library for preprocessing images
Home-page: https://github.com/pablo-francisco/img-preprocess-pipeline
Author: Pablo Francisco
Author-email: pablo.fco.melo@gmail.com
Requires-Python: >=3.10
License-File: LICENSE
Requires-Dist: numpy ==1.26.4
Requires-Dist: matplotlib ==3.9.1
Requires-Dist: tensorflow ==2.17.0
